splitn/__init__.py
splitn/help.py
splitn/main.py
splitn/parser.py
splitn/version.py
splitn-3.3.0.dist-info/LICENSE
splitn-3.3.0.dist-info/METADATA
splitn-3.3.0.dist-info/WHEEL
splitn-3.3.0.dist-info/entry_points.txt
splitn-3.3.0.dist-info/RECORD
