Metadata-Version: 2.1
Name: splitn
Version: 3.3.0
Summary: splitn is a CLI application that generates combinations of chars being a result of splitting strings
Home-page: https://github.com/born2Btiled/splitn
License: MIT
Author: Michał Warzocha
Author-email: warzocha.michal@icloud.com
Requires-Python: >=3.11,<4.0
Classifier: License :: OSI Approved :: MIT License
Classifier: Programming Language :: Python :: 3
Classifier: Programming Language :: Python :: 3.11
Requires-Dist: argparse (>=1.4.0,<2.0.0)
Requires-Dist: loguru (>=0.7.1,<0.8.0)
Requires-Dist: rich (>=13.5.2,<14.0.0)
Requires-Dist: rstr (>=3.2.1,<4.0.0)
Project-URL: Repository, https://github.com/born2Btiled/splitn
